{
    "EdgeInsiderVersions": {
        "last_updated": "July 04, 2025 09:15 AM EDT",
        "Version": [
            {
                "Name": "current",
                "Version": "138.0.3351.65",
                "Application_ID": "EDGE01",
                "Application_Name": "Microsoft Edge.app",
                "CFBundleVersion": "com.microsoft.edgemac",
                "Full_Update_Download": "https://msedge.sf.dl.delivery.mp.microsoft.com/filestreamingservice/files/84bbc955-86c8-45ec-a520-da2c4026e2e1/MicrosoftEdge-138.0.3351.65.pkg",
                "Full_Update_Sha1": "95e965335ad735f3ddf316e7749f5d14da7d0a4d",
                "Full_Update_Sha256": "ff125c9e9f5e15372e3a62affa4bb63ada11cb49226c78de1ca5b1b6ffdc3a1b",
                "Last_Update": "July 01, 2025 01:19 PM EDT"
            },
            {
                "Name": "canary",
                "Version": "140.0.3415.0",
                "Application_ID": "EDGE01",
                "Application_Name": "Microsoft Edge.app",
                "CFBundleVersion": "com.microsoft.edgemac",
                "Full_Update_Download": "https://msedge.sf.dl.delivery.mp.microsoft.com/filestreamingservice/files/96c254a8-dee2-4208-aac9-93a121211758/MicrosoftEdgeCanary-140.0.3415.0.pkg",
                "Full_Update_Sha1": "7c5f00ca2b2c6c05ecef1633bce5c97a882cc4d1",
                "Full_Update_Sha256": "0b3baeba51f5e4d6e5f4db818f719b3890a69c845e5d096fd1d0adfbadeaf147",
                "Last_Update": "July 04, 2025 08:47 AM EDT"
            },
            {
                "Name": "dev",
                "Version": "139.0.3405.13",
                "Application_ID": "EDGE01",
                "Application_Name": "Microsoft Edge.app",
                "CFBundleVersion": "com.microsoft.edgemac",
                "Full_Update_Download": "https://msedge.sf.dl.delivery.mp.microsoft.com/filestreamingservice/files/c7b30926-27cc-4921-b305-0d5ce209d35b/MicrosoftEdgeDev-139.0.3405.13.pkg",
                "Full_Update_Sha1": "e70d8d780c07de386f800da728078ec0d6770883",
                "Full_Update_Sha256": "daa52eaff88c678067cd03b41cf498386a33d75a3ff7aa2365c4d49ea532b007",
                "Last_Update": "July 03, 2025 02:12 PM EDT"
            },
            {
                "Name": "beta",
                "Version": "139.0.3405.13",
                "Application_ID": "EDGE01",
                "Application_Name": "Microsoft Edge.app",
                "CFBundleVersion": "com.microsoft.edgemac",
                "Full_Update_Download": "https://msedge.sf.dl.delivery.mp.microsoft.com/filestreamingservice/files/269344fa-2be7-4583-8926-309850dbc2f8/MicrosoftEdgeBeta-139.0.3405.13.pkg",
                "Full_Update_Sha1": "f1300afbdcea18782dac33d29fd6d35bc71fe100",
                "Full_Update_Sha256": "d26136e04fc35df123c9d895fb4bc76ec558313112390bbe0818a2d14120acd8",
                "Last_Update": "July 03, 2025 01:37 PM EDT"
            }
        ]
    }
}