{
    "last_updated": "March 20, 2025 09:33 PM EDT",
    "packages": [
        {
            "name": "Microsoft Office Suite",
            "application_id": "Data sourced from Outlook (CurrentThrottle)",
            "application_name": "Data sourced from Outlook (CurrentThrottle) ",
            "CFBundleVersion": "com.microsoft.office",
            "short_version": "16.95.0 (25030928)",
            "full_version": "16.95.25030928",
            "last_updated": "March 09, 2025",
            "min_os": "13.0",
            "update_download": "N/A",
            "latest_download": "https://go.microsoft.com/fwlink/?linkid=525133",
            "sha1": "9524470c70afd813ad58e36d3f8ea48800d936b2",
            "sha256": "7c1c73a0890cec5ee3d40d6bc7fb8e7461ba709c7df4a38500e8b4d736f3db31"
        },
        {
            "name": "Microsoft BusinessPro Suite",
            "application_id": "Data sourced from Excel (not manually specified)",
            "application_name": "Data sourced from Excel (not manually specified)",
            "CFBundleVersion": "com.microsoft.office",
            "short_version": "16.95.0 (25030928)",
            "full_version": "16.95.25030928",
            "last_updated": "March 09, 2025",
            "min_os": "13.0",
            "update_download": "N/A",
            "latest_download": "https://go.microsoft.com/fwlink/?linkid=2009112",
            "sha1": "c89f4c1e1ddd184005fb5985ca3f009972065095",
            "sha256": "09036a08056fe10480819ef4526fda9c3e8e1788f6bff70e3034e580e94d39e5"
        },
        {
            "name": "Word",
            "application_id": "MSWD2019",
            "application_name": "Microsoft Word.app",
            "CFBundleVersion": "com.microsoft.word",
            "short_version": "16.95.1 (25031528)",
            "full_version": "16.95.25031528",
            "last_updated": "March 15, 2025",
            "min_os": "13.0",
            "update_download": "https://officecdnmac.microsoft.com/pr/C1297A47-86C4-4C1F-97FA-950631F94777/MacAutoupdate/Microsoft_Word_16.95.25031528_Updater.pkg",
            "latest_download": "https://go.microsoft.com/fwlink/?linkid=525134",
            "sha1": "69638a8235498f96ea90816a662fe4f9af163366",
            "sha256": "71d647007d02faf9dd2c7911f91a1679cb3947b29203e381e0e2c88e05917446"
        },
        {
            "name": "Excel",
            "application_id": "XCEL2019",
            "application_name": "Microsoft Excel.app",
            "CFBundleVersion": "com.microsoft.excel",
            "short_version": "16.95.1 (25031528)",
            "full_version": "16.95.25031528",
            "last_updated": "March 15, 2025",
            "min_os": "13.0",
            "update_download": "https://officecdnmac.microsoft.com/pr/C1297A47-86C4-4C1F-97FA-950631F94777/MacAutoupdate/Microsoft_Excel_16.95.25031528_Updater.pkg",
            "latest_download": "https://go.microsoft.com/fwlink/?linkid=525135",
            "sha1": "37930fce2144e07e83d7311ae4a05d426e4f7fc3",
            "sha256": "61828b387ee351773c0654a2131fc93695ab24fcc992ba415a4bc454c852bfed"
        },
        {
            "name": "PowerPoint",
            "application_id": "PPT32019",
            "application_name": "Microsoft PowerPoint.app",
            "CFBundleVersion": "com.microsoft.powerpoint",
            "short_version": "16.95.1 (25031528)",
            "full_version": "16.95.25031528",
            "last_updated": "March 15, 2025",
            "min_os": "13.0",
            "update_download": "https://officecdnmac.microsoft.com/pr/C1297A47-86C4-4C1F-97FA-950631F94777/MacAutoupdate/Microsoft_PowerPoint_16.95.25031528_Updater.pkg",
            "latest_download": "https://go.microsoft.com/fwlink/?linkid=525136",
            "sha1": "36f0b45b36fb03d84be3d8251d869a5d91324a0e",
            "sha256": "b90d8af6016f9d19577bd82ea09bb8bfa64d9e83bbadf062bebab37cc0dba23a"
        },
        {
            "name": "Outlook",
            "application_id": "OPIM2019",
            "application_name": "Microsoft Outlook.app",
            "CFBundleVersion": "com.microsoft.outlook",
            "short_version": "16.95.1 (25031528)",
            "full_version": "16.95.25031528",
            "last_updated": "March 15, 2025",
            "min_os": "13.0",
            "update_download": "https://officecdnmac.microsoft.com/pr/C1297A47-86C4-4C1F-97FA-950631F94777/MacAutoupdate/Microsoft_Outlook_16.95.25031528_Updater.pkg",
            "latest_download": "https://go.microsoft.com/fwlink/?linkid=2228621",
            "sha1": "22034ca0e2db9b75dd5bc8bb9fd89fbd53d44299",
            "sha256": "310dd88039fdf01d1dbb6ef5ab9e3cd51c2fdd4b5c14ae42ea03fa4ee9548419"
        },
        {
            "name": "OneNote",
            "application_id": "ONMC2019",
            "application_name": "Microsoft OneNote.app",
            "CFBundleVersion": "com.microsoft.onenote",
            "short_version": "16.95.1 (25031528)",
            "full_version": "16.95.25031528",
            "last_updated": "March 15, 2025",
            "min_os": "13.0",
            "update_download": "https://officecdnmac.microsoft.com/pr/C1297A47-86C4-4C1F-97FA-950631F94777/MacAutoupdate/Microsoft_OneNote_16.95.25031528_Updater.pkg",
            "latest_download": "https://go.microsoft.com/fwlink/?linkid=820886",
            "sha1": "68ef291f0e6c7959e40008d8f44cf61a1a4c70e9",
            "sha256": "20173c3d2a6a3404875669ec3ab71159aed204abdad7ce5d00fb9c705229d00a"
        },
        {
            "name": "OneDrive",
            "application_id": "OneDrive.app",
            "application_name": "OneDrive.app",
            "CFBundleVersion": "com.microsoft.onedrive",
            "short_version": "25.031.0217",
            "full_version": "0217.0003",
            "last_updated": "March 20, 2025 09:33 PM EDT",
            "min_os": "N/A",
            "update_download": "https://oneclient.sfx.ms/Mac/Installers/25.031.0217.0003/OneDrive.pkg",
            "latest_download": "https://oneclient.sfx.ms/Mac/Installers/25.031.0217.0003/OneDrive.pkg",
            "sha1": "e1f1f54763089a523943e92895770fc8a5079f31",
            "sha256": "68faf7e84f93430ddd5c2ed711bd6e2372b14406df11509fab9c89b44b63e5f2"
        },
        {
            "name": "Skype",
            "application_id": "MSFB16",
            "application_name": "Skype for Business.app",
            "CFBundleVersion": "com.microsoft.skypeforbusiness",
            "short_version": "16.31.11",
            "full_version": "16.31.11",
            "last_updated": "September 05, 2024",
            "min_os": "10.14.0",
            "update_download": "https://officecdn.microsoft.com/pr/C1297A47-86C4-4C1F-97FA-950631F94777/MacAutoupdate/SkypeForBusinessUpdater-16.31.11.pkg",
            "latest_download": "https://go.microsoft.com/fwlink/?linkid=832978",
            "sha1": "91c6abad17552136cdbda3f7af12f1484f664fd2",
            "sha256": "81f484842e86a39c9f33abc4d35b4e7dbb87189ca3c424a6396e15d96ea2dbd5"
        },
        {
            "name": "Teams",
            "application_id": "TEAMS21",
            "application_name": "Microsoft Teams.app",
            "CFBundleVersion": "com.microsoft.teams",
            "short_version": "25044.2406.3471.4570",
            "full_version": "25044.2406.3471.4570",
            "last_updated": "March 05, 2025",
            "min_os": "13.0",
            "update_download": "https://statics.teams.cdn.office.net/production-osx/25044.2406.3471.4570/MicrosoftTeams.pkg",
            "latest_download": "https://go.microsoft.com/fwlink/?linkid=2249065",
            "sha1": "af83068015c80bd5a6516e37ce912e194883da70",
            "sha256": "1585139eff5d4879a5af493d2398219f7c3ae3e24e38ae62ff3d6e7525a3b451"
        },
        {
            "name": "Intune",
            "application_id": "IMCP01",
            "application_name": "Company Portal.app",
            "CFBundleVersion": "com.microsoft.intune.companyportal",
            "short_version": "5.2502.0",
            "full_version": "53.2502146.003",
            "last_updated": "February 18, 2025",
            "min_os": "11.0",
            "update_download": "https://officecdnmac.microsoft.com/pr/C1297A47-86C4-4C1F-97FA-950631F94777/MacAutoupdate/CompanyPortal_5.2502.0-Upgrade.pkg",
            "latest_download": "https://go.microsoft.com/fwlink/?linkid=853070",
            "sha1": "eac9feed6db618e39e366115ba788cd768f16aab",
            "sha256": "fad8352eb27bcc1a858e5f4959621349b4e45a0b1529893eb485b2840b609828"
        },
        {
            "name": "Edge",
            "application_id": "EDGE01",
            "application_name": "Microsoft Edge.app",
            "CFBundleVersion": "com.microsoft.edgemac",
            "short_version": "134.0.3124.51",
            "full_version": "134.3124.25030551",
            "last_updated": "March 05, 2025",
            "min_os": "11.0",
            "update_download": "https://officecdn-microsoft-com.akamaized.net/pr/03adf619-38c6-4249-95ff-4a01c0ffc962/MacAutoupdate/MicrosoftEdgeUpdate-134.0.3124.51.pkg",
            "latest_download": "https://go.microsoft.com/fwlink/?linkid=2093504",
            "sha1": "2cc335ddeec6261da54864df446f9db83a253497",
            "sha256": "5aa1d2fd4e35a177e98cddaee8b3edeedf6e765aef5a09d3872de96d5760778c"
        },
        {
            "name": "Defender For Endpoint",
            "application_id": "WDAV00",
            "application_name": "Microsoft Defender.app",
            "CFBundleVersion": "com.microsoft.defender.endpoint",
            "short_version": "101.25012.0008",
            "full_version": "101.25012.0008",
            "last_updated": "February 26, 2025",
            "min_os": "12.0",
            "update_download": "https://officecdnmac.microsoft.com/pr/C1297A47-86C4-4C1F-97FA-950631F94777/MacAutoupdate/wdav-upgrade.pkg",
            "latest_download": "https://go.microsoft.com/fwlink/?linkid=2097502",
            "sha1": "8285da2bf779b827087b71dc311bea285398a2c2",
            "sha256": "1a1e74a8c8cbb1dd1c00c37603b440c0749267d9525a64ea5e366e13783e0e2a"
        },
        {
            "name": "Defender for Consumers",
            "application_id": "WDAVCONSUMER",
            "application_name": "Microsoft Defender.app",
            "CFBundleVersion": "com.microsoft.defender.endpoint",
            "short_version": "101.25012.0008",
            "full_version": "101.25012.0008",
            "last_updated": "February 26, 2025",
            "min_os": "12.0",
            "update_download": "https://officecdnmac.microsoft.com/pr/C1297A47-86C4-4C1F-97FA-950631F94777/MacAutoupdate/Microsoft_Defender_101.25012.0008_Individuals_Installer.pkg",
            "latest_download": "https://go.microsoft.com/fwlink/?linkid=2247001",
            "sha1": "c3306a442fcb3b8e77b85156bac27f1c5a169668",
            "sha256": "4b48da50dc934ecd7127751496e31d9630e63cf019c976a4ecf1ae0cd293c49c"
        },
        {
            "name": "Defender Shim",
            "application_id": "WDAVSHIM",
            "application_name": "N/A",
            "CFBundleVersion": "com.microsoft.defender.endpoint",
            "short_version": "101.24080.0001",
            "full_version": "101.24080.0001",
            "last_updated": "October 16, 2024",
            "min_os": "12.0",
            "update_download": "https://officecdnmac.microsoft.com/pr/C1297A47-86C4-4C1F-97FA-950631F94777/MacAutoupdate/Microsoft_Defender_101.24080.0001_Individuals_Shim_Installer.pkg",
            "latest_download": "https://officecdnmac.microsoft.com/pr/C1297A47-86C4-4C1F-97FA-950631F94777/MacAutoupdate/Microsoft_Defender_101.24080.0001_Individuals_Shim_Installer.pkg",
            "sha1": "5101228ce261cfcc836d093889eef997e8f62dfd",
            "sha256": "3c455357808b67ec0ebbed62825e5d7f4652f3f53a1d3d58510e82099981bb51"
        },
        {
            "name": "Windows App",
            "application_id": "MSRD10",
            "application_name": "Windows App.app",
            "CFBundleVersion": "com.microsoft.windows.app",
            "short_version": "11.1.3",
            "full_version": "2532",
            "last_updated": "March 04, 2025",
            "min_os": "12.0",
            "update_download": "https://officecdnmac.microsoft.com/pr/C1297A47-86C4-4C1F-97FA-950631F94777/MacAutoupdate/Windows_App_11.1.3_updater.pkg",
            "latest_download": "https://go.microsoft.com/fwlink/?linkid=868963",
            "sha1": "3caa093439bac534bc065d0a34f62b6207c67f22",
            "sha256": "b4c1f5c59176eec80c841df4207a51ef6999d6c398c886e3dfa8525acdc5c2d3"
        },
        {
            "name": "Visual",
            "application_id": "N/A",
            "application_name": "Visual Studio Code.app",
            "CFBundleVersion": "com.microsoft.visualstudio",
            "short_version": "1.98.2",
            "full_version": "1.98.2",
            "last_updated": "March 12, 2025",
            "min_os": "N/A",
            "update_download": "https://vscode.download.prss.microsoft.com/dbazure/download/stable/ddc367ed5c8936efe395cffeec279b04ffd7db78/VSCode-darwin-universal.zip",
            "latest_download": "https://go.microsoft.com/fwlink/?linkid=2156837",
            "sha1": "293585143a3e1aa15300a0e3b34d97ce267122c9",
            "sha256": "a623aa0917bfb0f962e1ac005f9a431cfdbbf99612e1ddd5e1830aa8c0f7c420"
        },
        {
            "name": "MAU",
            "application_id": "MSau04",
            "application_name": "Microsoft AutoUpdate.app",
            "CFBundleVersion": "com.microsoft.autoupdate",
            "short_version": "4.78 (25031830)",
            "full_version": "4.78.25031830",
            "last_updated": "March 18, 2025",
            "min_os": "10.14.0",
            "update_download": "https://officecdnmac.microsoft.com/pr/C1297A47-86C4-4C1F-97FA-950631F94777/MacAutoupdate/Microsoft_AutoUpdate_4.78.25031830_Updater.pkg",
            "latest_download": "https://go.microsoft.com/fwlink/?linkid=830196",
            "sha1": "c1e02e0c916fa4ab2818558192a9da29b70394d5",
            "sha256": "8b08471fd5f11adee33c33c8f0b0634f5601218308fb89466a27ed0e66748952"
        },
        {
            "name": "Licensing Helper Tool",
            "application_id": "OLIC02",
            "application_name": "N/A",
            "CFBundleVersion": "com.microsoft.office.licensingV2.helper",
            "short_version": "16.77.0 (23091003)",
            "full_version": "16.77.23091003",
            "last_updated": "September 10, 2023",
            "min_os": "11.0",
            "update_download": "https://officecdnmac.microsoft.com/pr/C1297A47-86C4-4C1F-97FA-950631F94777/MacAutoupdate/Microsoft_OfficeLicensingHelper_16.77.23091003_Updater.pkg",
            "latest_download": "https://officecdnmac.microsoft.com/pr/C1297A47-86C4-4C1F-97FA-950631F94777/MacAutoupdate/Microsoft_OfficeLicensingHelper_16.77.23091003_Updater.pkg",
            "sha1": "cc58741e0243b5fb0682ca499b07c3a21060bb52",
            "sha256": "2ef5b5006534c0d20d46c7353f42a0dc1faff7d53ba89a3151ccf5102c059905"
        },
        {
            "name": "Quick Assist",
            "application_id": "MSQA01",
            "application_name": "Microsoft Quick Assist.app",
            "CFBundleVersion": "com.microsoft.quickassist",
            "short_version": "1.0.2411113",
            "full_version": "1.0.2411113",
            "last_updated": "November 12, 2024",
            "min_os": "12.0",
            "update_download": "https://officecdnmac.microsoft.com/pr/C1297A47-86C4-4C1F-97FA-950631F94777/MacAutoupdate/Microsoft_Quick_Assist_1.0.2411113_updater.pkg",
            "latest_download": "https://officecdnmac.microsoft.com/pr/C1297A47-86C4-4C1F-97FA-950631F94777/MacAutoupdate/Microsoft_Quick_Assist_1.0.2411113_updater.pkg",
            "sha1": "49db1be5bbb8091ea260631247d7de93c49afb9c",
            "sha256": "2fdab5e1815862c9b3583257c485b088aa46c86e5609cad09bfa13a3a092a0e1"
        },
        {
            "name": "Remote Help",
            "application_id": "MSRH01",
            "application_name": "Microsoft Remote Help.app",
            "CFBundleVersion": "com.microsoft.remotehelp",
            "short_version": "1.0.2501211",
            "full_version": "1.0.2501211",
            "last_updated": "January 24, 2025",
            "min_os": "12.0",
            "update_download": "https://officecdnmac.microsoft.com/pr/C1297A47-86C4-4C1F-97FA-950631F94777/MacAutoupdate/Microsoft_Remote_Help_1.0.2501211_updater.pkg",
            "latest_download": "https://officecdnmac.microsoft.com/pr/C1297A47-86C4-4C1F-97FA-950631F94777/MacAutoupdate/Microsoft_Remote_Help_1.0.2501211_updater.pkg",
            "sha1": "304f3a4247c99d016df8734fa5d8524591ac1b14",
            "sha256": "8ffe881653742ce83ebaf60636906f7f47596569e2c36d71aa33f6c85f70536e"
        }
    ]
}