{
    "EdgeInsiderVersions": {
        "last_updated": "August 21, 2025 01:07 AM EDT",
        "Version": [
            {
                "Name": "current",
                "Version": "139.0.3405.102",
                "Application_ID": "EDGE01",
                "Application_Name": "Microsoft Edge.app",
                "CFBundleVersion": "com.microsoft.edgemac",
                "Full_Update_Download": "https://msedge.sf.dl.delivery.mp.microsoft.com/filestreamingservice/files/4d599f34-3ef7-4f04-bd4b-6f35be25008c/MicrosoftEdge-139.0.3405.102.pkg",
                "Full_Update_Sha1": "041ee2ac752a5a4c845ef5d9aaae11d3cfe0321f",
                "Full_Update_Sha256": "c5edb687ac110cabedf989706a6e9fade4f30375ef194f155fade830fc8837be",
                "Last_Update": "August 17, 2025 03:19 AM EDT"
            },
            {
                "Name": "canary",
                "Version": "141.0.3511.0",
                "Application_ID": "EDGE01",
                "Application_Name": "Microsoft Edge.app",
                "CFBundleVersion": "com.microsoft.edgemac",
                "Full_Update_Download": "https://msedge.sf.dl.delivery.mp.microsoft.com/filestreamingservice/files/b2c4b57a-f793-4767-9701-eca9aa4d09bc/MicrosoftEdgeCanary-141.0.3511.0.pkg",
                "Full_Update_Sha1": "c0ee1013d2d738e36841c3d7967666b977b7b73d",
                "Full_Update_Sha256": "460f75bb1f6a263eda2d97a3357d50ff65fd96dcd0c0119c23579cadcfc7a38d",
                "Last_Update": "August 20, 2025 06:00 PM EDT"
            },
            {
                "Name": "dev",
                "Version": "141.0.3500.1",
                "Application_ID": "EDGE01",
                "Application_Name": "Microsoft Edge.app",
                "CFBundleVersion": "com.microsoft.edgemac",
                "Full_Update_Download": "https://msedge.sf.dl.delivery.mp.microsoft.com/filestreamingservice/files/84ce67ce-d9ab-4e85-b9c0-888d3fa625e7/MicrosoftEdgeDev-141.0.3500.1.pkg",
                "Full_Update_Sha1": "56697a0e2c2cbf999387905ec08dc3308b927f19",
                "Full_Update_Sha256": "58845dd72ed8fa689e12c2e74bdb0fad3aac11ad6328d0e48d113d3ca2969c85",
                "Last_Update": "August 20, 2025 01:10 PM EDT"
            },
            {
                "Name": "beta",
                "Version": "140.0.3485.14",
                "Application_ID": "EDGE01",
                "Application_Name": "Microsoft Edge.app",
                "CFBundleVersion": "com.microsoft.edgemac",
                "Full_Update_Download": "https://msedge.sf.dl.delivery.mp.microsoft.com/filestreamingservice/files/c5e802ee-904f-41d4-a040-14c4bebd4a29/MicrosoftEdgeBeta-140.0.3485.14.pkg",
                "Full_Update_Sha1": "9cc28689c0705e6a1b222b8fa9f6deb526dfd37d",
                "Full_Update_Sha256": "75a4983d393d305b8966c156a3708c1047623b5457d2a3e54c547e2fc3989b55",
                "Last_Update": "August 18, 2025 05:47 PM EDT"
            }
        ]
    }
}