<?xml version="1.0" ?>
<latest>
    <last_updated>December 14, 2025 06:06 AM EST</last_updated>
    <package>
        <name>Word</name>
        <application_id>MSWD2019</application_id>
        <application_name>Microsoft Word.app</application_name>
        <CFBundleVersion>com.microsoft.word</CFBundleVersion>
        <short_version>16.105.0 (25120928)</short_version>
        <full_version>16.105.25120928</full_version>
        <last_updated>December 09, 2025</last_updated>
        <min_os>14.0</min_os>
        <update_download>https://res.public.onecdn.static.microsoft/mro1cdnstorage/4B2D7701-0A4F-49C8-B4CB-0C2D4043F51F/MacAutoupdate/Microsoft_Word_16.105.25120928_Updater.pkg</update_download>
        <latest_download>https://res.public.onecdn.static.microsoft/mro1cdnstorage/4B2D7701-0A4F-49C8-B4CB-0C2D4043F51F/MacAutoupdate/Microsoft_Word_16.105.25120928_Updater.pkg</latest_download>
        <sha1>a27fc0deb0c9f1e0998eae230ab6573243659c34</sha1>
        <sha256>d7b9fc52c64a76b159c56ac9c68d37aefe21d3c2b71f58c1ad5af6a3b85268e6</sha256>
    </package>
    <package>
        <name>Excel</name>
        <application_id>XCEL2019</application_id>
        <application_name>Microsoft Excel.app</application_name>
        <CFBundleVersion>com.microsoft.excel</CFBundleVersion>
        <short_version>16.105.0 (25120928)</short_version>
        <full_version>16.105.25120928</full_version>
        <last_updated>December 09, 2025</last_updated>
        <min_os>14.0</min_os>
        <update_download>https://res.public.onecdn.static.microsoft/mro1cdnstorage/4B2D7701-0A4F-49C8-B4CB-0C2D4043F51F/MacAutoupdate/Microsoft_Excel_16.105.25120928_Updater.pkg</update_download>
        <latest_download>https://res.public.onecdn.static.microsoft/mro1cdnstorage/4B2D7701-0A4F-49C8-B4CB-0C2D4043F51F/MacAutoupdate/Microsoft_Excel_16.105.25120928_Updater.pkg</latest_download>
        <sha1>e8aabfa5e1df432f8758a990f9c9057b98dc16f0</sha1>
        <sha256>a03aa1196ab5648576f15f71c6dc5870093c2e0b488125e3ad12d8d3d88220ec</sha256>
    </package>
    <package>
        <name>PowerPoint</name>
        <application_id>PPT32019</application_id>
        <application_name>Microsoft PowerPoint.app</application_name>
        <CFBundleVersion>com.microsoft.powerpoint</CFBundleVersion>
        <short_version>16.105.0 (25120928)</short_version>
        <full_version>16.105.25120928</full_version>
        <last_updated>December 09, 2025</last_updated>
        <min_os>14.0</min_os>
        <update_download>https://res.public.onecdn.static.microsoft/mro1cdnstorage/4B2D7701-0A4F-49C8-B4CB-0C2D4043F51F/MacAutoupdate/Microsoft_PowerPoint_16.105.25120928_Updater.pkg</update_download>
        <latest_download>https://res.public.onecdn.static.microsoft/mro1cdnstorage/4B2D7701-0A4F-49C8-B4CB-0C2D4043F51F/MacAutoupdate/Microsoft_PowerPoint_16.105.25120928_Updater.pkg</latest_download>
        <sha1>f474f5f0a4925d44d3a4e4568a5f06a6832f0ace</sha1>
        <sha256>18ca4f8b3b47b5ab6684f4f1323bb71f735cbab8b87c822983f506b96ea3b4a3</sha256>
    </package>
    <package>
        <name>Outlook</name>
        <application_id>OPIM2019</application_id>
        <application_name>Microsoft Outlook.app</application_name>
        <CFBundleVersion>com.microsoft.outlook</CFBundleVersion>
        <short_version>16.105.0 (25120928)</short_version>
        <full_version>16.105.25120928</full_version>
        <last_updated>December 09, 2025</last_updated>
        <min_os>14.0</min_os>
        <update_download>https://res.public.onecdn.static.microsoft/mro1cdnstorage/4B2D7701-0A4F-49C8-B4CB-0C2D4043F51F/MacAutoupdate/Microsoft_Outlook_16.105.25120928_Updater.pkg</update_download>
        <latest_download>https://res.public.onecdn.static.microsoft/mro1cdnstorage/4B2D7701-0A4F-49C8-B4CB-0C2D4043F51F/MacAutoupdate/Microsoft_Outlook_16.105.25120928_Updater.pkg</latest_download>
        <sha1>649597cb2e18e143bdd577f994a8478623accf67</sha1>
        <sha256>cfef07a5e70dbe155657c0dbf03e39a3f9157092bd9f1daf74d7c5e864b3ea50</sha256>
    </package>
    <package>
        <name>OneNote</name>
        <application_id>ONMC2019</application_id>
        <application_name>Microsoft OneNote.app</application_name>
        <CFBundleVersion>com.microsoft.onenote</CFBundleVersion>
        <short_version>16.105.0 (25120928)</short_version>
        <full_version>16.105.25120928</full_version>
        <last_updated>December 09, 2025</last_updated>
        <min_os>14.0</min_os>
        <update_download>https://res.public.onecdn.static.microsoft/mro1cdnstorage/4B2D7701-0A4F-49C8-B4CB-0C2D4043F51F/MacAutoupdate/Microsoft_OneNote_16.105.25120928_Updater.pkg</update_download>
        <latest_download>https://res.public.onecdn.static.microsoft/mro1cdnstorage/4B2D7701-0A4F-49C8-B4CB-0C2D4043F51F/MacAutoupdate/Microsoft_OneNote_16.105.25120928_Updater.pkg</latest_download>
        <sha1>175090f0906d3700c4777a1d445b6d1af929e534</sha1>
        <sha256>5b3df71f17fd10b965d4ebcd95337cbdad66ece059027d72facc7348667a512b</sha256>
    </package>
    <package>
        <name>Skype</name>
        <application_id>MSFB16</application_id>
        <application_name>Skype for Business.app</application_name>
        <CFBundleVersion>com.microsoft.skypeforbusiness</CFBundleVersion>
        <short_version>16.31.10</short_version>
        <full_version>16.31.10</full_version>
        <last_updated>September 05, 2024</last_updated>
        <min_os>10.14.0</min_os>
        <update_download>https://officecdn.microsoft.com/pr/4B2D7701-0A4F-49C8-B4CB-0C2D4043F51F/MacAutoupdate/SkypeForBusinessUpdater-16.31.10.pkg</update_download>
        <latest_download>https://officecdn.microsoft.com/pr/4B2D7701-0A4F-49C8-B4CB-0C2D4043F51F/MacAutoupdate/SkypeForBusinessUpdater-16.31.10.pkg</latest_download>
        <sha1>68fb89f16a62e088cbe140fd1a3a13f65846c827</sha1>
        <sha256>5028b8911b3076e6b1ab18ac520fdbf390ecd7da8d57986e86b2c9351a93d175</sha256>
    </package>
    <package>
        <name>Teams</name>
        <application_id>TEAMS21</application_id>
        <application_name>Microsoft Teams.app</application_name>
        <CFBundleVersion>com.microsoft.teams</CFBundleVersion>
        <short_version>25338.2401.4166.1382</short_version>
        <full_version>25338.2401.4166.1382</full_version>
        <last_updated>December 05, 2025</last_updated>
        <min_os>13.0</min_os>
        <update_download>https://teamsinstaller.public.onecdn.static.microsoft/production-osx/25338.2401.4166.1382/MicrosoftTeams.pkg</update_download>
        <latest_download>https://teamsinstaller.public.onecdn.static.microsoft/production-osx/25338.2401.4166.1382/MicrosoftTeams.pkg</latest_download>
        <sha1>f1a39e6cd566d020a4ce482e2d9f8a442437a90d</sha1>
        <sha256>ede19dcfd9a8f6eb47ff2df57ee6a6b07ea78e4d4656567dd13f642dd20fbe06</sha256>
    </package>
    <package>
        <name>Intune</name>
        <application_id>IMCP01</application_id>
        <application_name>Company Portal.app</application_name>
        <CFBundleVersion>com.microsoft.intune.companyportal</CFBundleVersion>
        <short_version>5.2511.0</short_version>
        <full_version>53.2512473.003</full_version>
        <last_updated>December 05, 2025</last_updated>
        <min_os>11.0</min_os>
        <update_download>https://res.public.onecdn.static.microsoft/mro1cdnstorage/4B2D7701-0A4F-49C8-B4CB-0C2D4043F51F/MacAutoupdate/CompanyPortal_5.2511.0-Upgrade.pkg</update_download>
        <latest_download>https://res.public.onecdn.static.microsoft/mro1cdnstorage/4B2D7701-0A4F-49C8-B4CB-0C2D4043F51F/MacAutoupdate/CompanyPortal_5.2511.0-Upgrade.pkg</latest_download>
        <sha1>bd1f11bf8d59603bba8d87d03785ae67fff7aceb</sha1>
        <sha256>ca5084beb742e6814ce7f3b97379d7d6ba559f37b953bbb6ffd9dea5115b7a56</sha256>
    </package>
    <package>
        <name>Edge</name>
        <application_id>EDGE01</application_id>
        <application_name>Microsoft Edge.app</application_name>
        <CFBundleVersion>com.microsoft.edgemac</CFBundleVersion>
        <short_version>134.0.3124.51</short_version>
        <full_version>134.3124.25030551</full_version>
        <last_updated>March 05, 2025</last_updated>
        <min_os>11.0</min_os>
        <update_download>https://officecdn-microsoft-com.akamaized.net/pr/03adf619-38c6-4249-95ff-4a01c0ffc962/MacAutoupdate/MicrosoftEdgeUpdate-134.0.3124.51.pkg</update_download>
        <latest_download>https://officecdn-microsoft-com.akamaized.net/pr/03adf619-38c6-4249-95ff-4a01c0ffc962/MacAutoupdate/MicrosoftEdgeUpdate-134.0.3124.51.pkg</latest_download>
        <sha1>85d10b2ba411bc62513ead7c6cc4dde3b66ad2a1</sha1>
        <sha256>c6f0e912f0c98cfdbaf63812bbeb831f3ab003c99c9de4882ddee75a0ce64559</sha256>
    </package>
    <package>
        <name>Defender For Endpoint</name>
        <application_id>WDAV00</application_id>
        <application_name>Microsoft Defender.app</application_name>
        <CFBundleVersion>com.microsoft.defender.endpoint</CFBundleVersion>
        <short_version>101.25102.0016</short_version>
        <full_version>101.25102.0016</full_version>
        <last_updated>November 30, 2025</last_updated>
        <min_os>12.0</min_os>
        <update_download>https://officecdnmac.microsoft.com/pr/4B2D7701-0A4F-49C8-B4CB-0C2D4043F51F/MacAutoupdate/wdav-upgrade.pkg</update_download>
        <latest_download>https://officecdnmac.microsoft.com/pr/4B2D7701-0A4F-49C8-B4CB-0C2D4043F51F/MacAutoupdate/wdav-upgrade.pkg</latest_download>
        <sha1>886a61d45fca2541bf90ea817e41dbdb67f5dc81</sha1>
        <sha256>fe637a4d2c2047adc622740ba89b4c324b5674485bee98700cf49b155d251c1f</sha256>
    </package>
    <package>
        <name>Defender For Consumers</name>
        <application_id>WDAVCONSUMER</application_id>
        <application_name>Microsoft Defender.app</application_name>
        <CFBundleVersion>com.microsoft.defender.endpoint</CFBundleVersion>
        <short_version>101.25102.0016</short_version>
        <full_version>101.25102.0016</full_version>
        <last_updated>November 30, 2025</last_updated>
        <min_os>12.0</min_os>
        <update_download>https://officecdnmac.microsoft.com/pr/4B2D7701-0A4F-49C8-B4CB-0C2D4043F51F/MacAutoupdate/Microsoft_Defender_101.25102.0016_Individuals_Installer.pkg</update_download>
        <latest_download>https://officecdnmac.microsoft.com/pr/4B2D7701-0A4F-49C8-B4CB-0C2D4043F51F/MacAutoupdate/Microsoft_Defender_101.25102.0016_Individuals_Installer.pkg</latest_download>
        <sha1>ce57fc58fafd0ce3886bd82dcecf3705196257f8</sha1>
        <sha256>be9b0da79550d8cc6d4adea3ed6f5395799b9def020329a646f999002b812c49</sha256>
    </package>
    <package>
        <name>Defender Shim</name>
        <application_id>WDAVSHIM</application_id>
        <application_name>Microsoft Defender.app</application_name>
        <CFBundleVersion>com.microsoft.defender.endpoint</CFBundleVersion>
        <short_version>101.24080.0001</short_version>
        <full_version>101.24080.0001</full_version>
        <last_updated>October 16, 2024</last_updated>
        <min_os>12.0</min_os>
        <update_download>https://officecdnmac.microsoft.com/pr/4B2D7701-0A4F-49C8-B4CB-0C2D4043F51F/MacAutoupdate/Microsoft_Defender_101.24080.0001_Individuals_Shim_Installer.pkg</update_download>
        <latest_download>https://officecdnmac.microsoft.com/pr/4B2D7701-0A4F-49C8-B4CB-0C2D4043F51F/MacAutoupdate/Microsoft_Defender_101.24080.0001_Individuals_Shim_Installer.pkg</latest_download>
        <sha1>5101228ce261cfcc836d093889eef997e8f62dfd</sha1>
        <sha256>3c455357808b67ec0ebbed62825e5d7f4652f3f53a1d3d58510e82099981bb51</sha256>
    </package>
    <package>
        <name>Visual</name>
        <application_id>N/A</application_id>
        <application_name>Visual Studio Code - Insiders.app</application_name>
        <CFBundleVersion>com.microsoft.VSCodeInsiders</CFBundleVersion>
        <short_version>1.108.0-</short_version>
        <full_version>1.108.0-insider</full_version>
        <last_updated>December 12, 2025</last_updated>
        <min_os>N/A</min_os>
        <update_download>https://vscode.download.prss.microsoft.com/dbazure/download/insider/9ba40f8204f1b4cb092f9585b19ab3f26d0a588c/VSCode-darwin-universal.zip</update_download>
        <latest_download>https://code.visualstudio.com/sha/download?build=insider&amp;os=darwin-universal</latest_download>
        <sha1>28c1bad4b3dd1883c2e1c8f0e9071299fbde9c3d</sha1>
        <sha256>db8f051245ceab8f40874f897c228e5e157d715848af3b0bf71fefa5f77a24f8</sha256>
    </package>
    <package>
        <name>Copilot</name>
        <application_id>MSCP10</application_id>
        <application_name>Microsoft 365 Copilot.app</application_name>
        <CFBundleVersion>com.microsoft.m365copilot</CFBundleVersion>
        <short_version>1.2512 (1202)</short_version>
        <full_version>1.2512.1202</full_version>
        <last_updated>December 12, 2025</last_updated>
        <min_os>14.0</min_os>
        <update_download>https://res.public.onecdn.static.microsoft/mro1cdnstorage/4B2D7701-0A4F-49C8-B4CB-0C2D4043F51F/MacAutoupdate/Microsoft_365_Copilot_universal_1.2512.1202_Updater.pkg</update_download>
        <latest_download>https://res.public.onecdn.static.microsoft/mro1cdnstorage/4B2D7701-0A4F-49C8-B4CB-0C2D4043F51F/MacAutoupdate/Microsoft_365_Copilot_universal_1.2512.1202_Updater.pkg</latest_download>
        <sha1>dd8d92d01472b049ea74462089bbc831c4267431</sha1>
        <sha256>160e49e3d1138329750e94abc54c2c2287faf9b1091ba6f10d9fd9eb77e46d69</sha256>
    </package>
    <package>
        <name>MAU</name>
        <application_id>MSau04</application_id>
        <application_name>Microsoft AutoUpdate.app</application_name>
        <CFBundleVersion>com.microsoft.autoupdate</CFBundleVersion>
        <short_version>4.81 (25121042)</short_version>
        <full_version>4.81.25121042</full_version>
        <last_updated>December 10, 2025</last_updated>
        <min_os>12.0</min_os>
        <update_download>https://res.public.onecdn.static.microsoft/mro1cdnstorage/4B2D7701-0A4F-49C8-B4CB-0C2D4043F51F/MacAutoupdate/Microsoft_AutoUpdate_4.81.25121042_Updater.pkg</update_download>
        <latest_download>https://res.public.onecdn.static.microsoft/mro1cdnstorage/4B2D7701-0A4F-49C8-B4CB-0C2D4043F51F/MacAutoupdate/Microsoft_AutoUpdate_4.81.25121042_Updater.pkg</latest_download>
        <sha1>f5343c741a4bfbb805b14fa7cf842f7db05f5199</sha1>
        <sha256>bf281c826c18a0a8e8fd8abe1c9bcbc8deb9b25c251fc6b219e3e5dd7452aa21</sha256>
    </package>
    <package>
        <name>Windows App Beta</name>
        <application_id>N/A</application_id>
        <application_name>Windows App Beta.app</application_name>
        <CFBundleVersion>com.microsoft.windows.app</CFBundleVersion>
        <short_version>11.3.1</short_version>
        <full_version>11.3.1</full_version>
        <last_updated>December 04, 2025</last_updated>
        <min_os>N/A</min_os>
        <update_download>https://appcenter-filemanagement-distrib1ede6f06e-a6b7akbshagxhcfs.z01.azurefd.net/b5383ca3-bf46-478c-9a92-dc55c0d444f9/Windows%20App%20Beta.app.zip?sv=2019-07-07&amp;sr=c&amp;sig=%2B%2FUA4aFrJ00hp%2FGrsLOseVM9o12ieq4cq3csfMHKnEA%3D&amp;skoid=05571020-ed2f-4af9-8176-0df11ddebe41&amp;sktid=975f013f-7f24-47e8-a7d3-abc4752bf346&amp;skt=2025-12-04T22%3A46%3A46Z&amp;ske=2025-12-05T22%3A51%3A46Z&amp;sks=b&amp;skv=2019-07-07&amp;se=2025-12-05T22%3A51%3A46Z&amp;sp=r</update_download>
        <latest_download>https://appcenter-filemanagement-distrib1ede6f06e-a6b7akbshagxhcfs.z01.azurefd.net/b5383ca3-bf46-478c-9a92-dc55c0d444f9/Windows%20App%20Beta.app.zip?sv=2019-07-07&amp;sr=c&amp;sig=%2B%2FUA4aFrJ00hp%2FGrsLOseVM9o12ieq4cq3csfMHKnEA%3D&amp;skoid=05571020-ed2f-4af9-8176-0df11ddebe41&amp;sktid=975f013f-7f24-47e8-a7d3-abc4752bf346&amp;skt=2025-12-04T22%3A46%3A46Z&amp;ske=2025-12-05T22%3A51%3A46Z&amp;sks=b&amp;skv=2019-07-07&amp;se=2025-12-05T22%3A51%3A46Z&amp;sp=r</latest_download>
        <sha1>4e9527370abe1600d0936c60d2da661f7f8a3b00</sha1>
        <sha256>08ae9b247f28c1a5a5465b60c9aaa7b3277f698c6d02ab3898550061cd8f4a15</sha256>
    </package>
</latest>
